odoo/addons/survey_legal/README.rst
odoo/addons/survey_legal/__init__.py
odoo/addons/survey_legal/__manifest__.py
odoo/addons/survey_legal/controllers/__init__.py
odoo/addons/survey_legal/controllers/main.py
odoo/addons/survey_legal/i18n/it.po
odoo/addons/survey_legal/i18n/survey_legal.pot
odoo/addons/survey_legal/models/__init__.py
odoo/addons/survey_legal/models/survey.py
odoo/addons/survey_legal/models/survey_user_input.py
odoo/addons/survey_legal/readme/CONFIGURE.rst
odoo/addons/survey_legal/readme/CONTRIBUTORS.rst
odoo/addons/survey_legal/readme/DESCRIPTION.rst
odoo/addons/survey_legal/static/description/icon.png
odoo/addons/survey_legal/static/description/index.html
odoo/addons/survey_legal/views/survey_templates.xml
odoo/addons/survey_legal/views/survey_user_input_views.xml
odoo/addons/survey_legal/views/survey_views.xml
odoo13_addon_survey_legal-13.0.1.0.1.dev6.dist-info/METADATA
odoo13_addon_survey_legal-13.0.1.0.1.dev6.dist-info/WHEEL
odoo13_addon_survey_legal-13.0.1.0.1.dev6.dist-info/top_level.txt
odoo13_addon_survey_legal-13.0.1.0.1.dev6.dist-info/RECORD
