Metadata-Version: 2.1
Name: odoo13-addon-survey-legal
Version: 13.0.1.0.1.dev6
Summary: Require legal terms before survey submit
Home-page: https://github.com/OCA/survey
Author: Tecnativa, Odoo Community Association (OCA)
Author-email: support@odoo-community.org
License: AGPL-3
Platform: UNKNOWN
Classifier: Programming Language :: Python
Classifier: Framework :: Odoo
Classifier: Framework :: Odoo :: 13.0
Classifier: License :: OSI Approved :: GNU Affero General Public License v3
Classifier: Development Status :: 4 - Beta
Requires-Python: >=3.5
Requires-Dist: odoo13-addon-website-legal-page
Requires-Dist: odoo <13.1dev,>=13.0a
